COPYING.txt
MANIFEST.in
README.rst
setup.cfg
setup.py
tasks.py
Tailbone.egg-info/PKG-INFO
Tailbone.egg-info/SOURCES.txt
Tailbone.egg-info/dependency_links.txt
Tailbone.egg-info/entry_points.txt
Tailbone.egg-info/requires.txt
Tailbone.egg-info/top_level.txt
tailbone/__init__.py
tailbone/_version.py
tailbone/app.py
tailbone/asgi.py
tailbone/auth.py
tailbone/beaker.py
tailbone/cleanup.py
tailbone/config.py
tailbone/db.py
tailbone/diffs.py
tailbone/exceptions.py
tailbone/handler.py
tailbone/helpers.py
tailbone/menus.py
tailbone/progress.py
tailbone/providers.py
tailbone/subscribers.py
tailbone/tweens.py
tailbone/util.py
tailbone/webapi.py
tailbone/api/__init__.py
tailbone/api/auth.py
tailbone/api/common.py
tailbone/api/core.py
tailbone/api/customers.py
tailbone/api/essentials.py
tailbone/api/labels.py
tailbone/api/master.py
tailbone/api/master2.py
tailbone/api/people.py
tailbone/api/products.py
tailbone/api/upgrades.py
tailbone/api/users.py
tailbone/api/vendors.py
tailbone/api/workorders.py
tailbone/api/batch/__init__.py
tailbone/api/batch/core.py
tailbone/api/batch/inventory.py
tailbone/api/batch/labels.py
tailbone/api/batch/ordering.py
tailbone/api/batch/receiving.py
tailbone/forms/__init__.py
tailbone/forms/common.py
tailbone/forms/core.py
tailbone/forms/receiving.py
tailbone/forms/types.py
tailbone/forms/widgets.py
tailbone/grids/__init__.py
tailbone/grids/core.py
tailbone/grids/filters.py
tailbone/reports/inventory_worksheet.mako
tailbone/reports/ordering_worksheet.mako
tailbone/static/__init__.py
tailbone/static/robots.txt
tailbone/static/css/base.css
tailbone/static/css/codehilite.css
tailbone/static/css/diffs.css
tailbone/static/css/filters.css
tailbone/static/css/forms.css
tailbone/static/css/grids.css
tailbone/static/css/grids.rowstatus.css
tailbone/static/css/layout.css
tailbone/static/css/normalize.css
tailbone/static/css/perms.css
tailbone/static/css/progress.css
tailbone/static/css/purchases.css
tailbone/static/css/schedule_print.css
tailbone/static/css/timesheet.css
tailbone/static/files/newproduct_template.xlsx
tailbone/static/files/vendor_catalog_template.xlsx
tailbone/static/img/Hymenocephalus_italicus.jpg
tailbone/static/img/delete.png
