Metadata-Version: 2.1
Name: Tailbone
Version: 0.11.7
Summary: Backoffice Web Application for Rattail
Home-page: http://rattailproject.org/
Author: Lance Edgar
Author-email: lance@edbob.org
License: GNU GPL v3
Classifier: Development Status :: 4 - Beta
Classifier: Environment :: Web Environment
Classifier: Framework :: Pyramid
Classifier: Intended Audience :: Developers
Classifier: License :: OSI Approved :: GNU General Public License v3 or later (GPLv3+)
Classifier: Natural Language :: English
Classifier: Operating System :: OS Independent
Classifier: Programming Language :: Python
Classifier: Programming Language :: Python :: 3
Classifier: Programming Language :: Python :: 3.6
Classifier: Programming Language :: Python :: 3.7
Classifier: Programming Language :: Python :: 3.8
Classifier: Programming Language :: Python :: 3.9
Classifier: Programming Language :: Python :: 3.10
Classifier: Programming Language :: Python :: 3.11
Classifier: Topic :: Internet :: WWW/HTTP
Classifier: Topic :: Office/Business
Classifier: Topic :: Software Development :: Libraries :: Python Modules
License-File: COPYING.txt
Requires-Dist: asgiref
Requires-Dist: colander
Requires-Dist: ColanderAlchemy
Requires-Dist: cornice
Requires-Dist: cornice-swagger
Requires-Dist: deform
Requires-Dist: humanize
Requires-Dist: Mako
Requires-Dist: markdown
Requires-Dist: openpyxl
Requires-Dist: paginate
Requires-Dist: paginate_sqlalchemy
Requires-Dist: passlib
Requires-Dist: Pillow
Requires-Dist: pyramid>=2
Requires-Dist: pyramid_beaker
Requires-Dist: pyramid_deform
Requires-Dist: pyramid_exclog
Requires-Dist: pyramid_fanstatic
Requires-Dist: pyramid_mako
Requires-Dist: pyramid_retry
Requires-Dist: pyramid_tm
Requires-Dist: rattail[bouncer,db]
Requires-Dist: sa-filters
Requires-Dist: simplejson
Requires-Dist: transaction
Requires-Dist: waitress
Requires-Dist: WebHelpers2
Requires-Dist: zope.sqlalchemy>=1.5
Provides-Extra: docs
Requires-Dist: Sphinx; extra == "docs"
Requires-Dist: sphinx-rtd-theme; extra == "docs"
Provides-Extra: tests
Requires-Dist: coverage; extra == "tests"
Requires-Dist: mock; extra == "tests"
Requires-Dist: pytest; extra == "tests"
Requires-Dist: pytest-cov; extra == "tests"
